CLASSIFIERS.txt
LICENSE.txt
MANIFEST.in
README.rst
requirements.pip
setup.py
src/django_historicalrecords_rca.egg-info/PKG-INFO
src/django_historicalrecords_rca.egg-info/SOURCES.txt
src/django_historicalrecords_rca.egg-info/dependency_links.txt
src/django_historicalrecords_rca.egg-info/top_level.txt
src/history/__init__.py
src/history/apps.py
src/history/manager.py
src/history/models.py
src/history/utils.py