Metadata-Version: 1.1
Name: django-historicalrecords-rca
Version: 1.2.5
Summary: Marty Alchin's HistoricalRecords from the ProDjango book.
Home-page: http://github.com/rca/django-historicalrecords
Author: Marty Alchin
Author-email: UNKNOWN
License: BSD
Platform: UNKNOWN
Classifier: Development Status :: 5 - Production/Stable
Classifier: Intended Audience :: Developers
Classifier: License :: OSI Approved :: BSD License
Classifier: Operating System :: OS Independent
Classifier: Programming Language :: Python
Classifier: Framework :: Django
Classifier: Topic :: Software Development :: Libraries :: Python Modules
